odoo/addons/base_user_show_email/README.rst
odoo/addons/base_user_show_email/__init__.py
odoo/addons/base_user_show_email/__manifest__.py
odoo/addons/base_user_show_email/readme/CONTRIBUTORS.rst
odoo/addons/base_user_show_email/readme/DESCRIPTION.rst
odoo/addons/base_user_show_email/static/description/icon.png
odoo/addons/base_user_show_email/static/description/index.html
odoo/addons/base_user_show_email/views/login_layout.xml
odoo/addons/base_user_show_email/views/res_users_view.xml
odoo12_addon_base_user_show_email-12.0.1.0.0.dist-info/METADATA
odoo12_addon_base_user_show_email-12.0.1.0.0.dist-info/RECORD
odoo12_addon_base_user_show_email-12.0.1.0.0.dist-info/WHEEL
odoo12_addon_base_user_show_email-12.0.1.0.0.dist-info/top_level.txt
